{
	"name": "increm_data_pipeline",
	"properties": {
		"activities": [
			{
				"name": "Copy_Increm_Data",
				"type": "Copy",
				"dependsOn": [
					{
						"activity": "last_load",
						"dependencyConditions": [
							"Succeeded"
						]
					},
					{
						"activity": "current_load",
						"dependencyConditions": [
							"Succeeded"
						]
					}
				],
				"policy": {
					"timeout": "0.12:00:00",
					"retry": 0,
					"retryIntervalInSeconds": 30,
					"secureOutput": false,
					"secureInput": false
				},
				"userProperties": [],
				"typeProperties": {
					"source": {
						"type": "AzureSqlSource",
						"sqlReaderQuery": {
							"value": "SELECT * FROM source_cars_data WHERE Date_ID > '@{activity('last_load').output.firstRow.last_load}' AND Date_ID <= '@{activity('current_load').output.firstRow.max_date}' ",
							"type": "Expression"
						},
						"queryTimeout": "02:00:00",
						"partitionOption": "None"
					},
					"sink": {
						"type": "ParquetSink",
						"storeSettings": {
							"type": "AzureBlobFSWriteSettings"
						},
						"formatSettings": {
							"type": "ParquetWriteSettings"
						}
					},
					"enableStaging": false,
					"translator": {
						"type": "TabularTranslator",
						"typeConversion": true,
						"typeConversionSettings": {
							"allowDataTruncation": true,
							"treatBooleanAsNumber": false
						}
					}
				},
				"inputs": [
					{
						"referenceName": "ds_sqldb",
						"type": "DatasetReference",
						"parameters": {
							"table_name": "source_cars_data"
						}
					}
				],
				"outputs": [
					{
						"referenceName": "ds_bronze",
						"type": "DatasetReference"
					}
				]
			},
			{
				"name": "last_load",
				"type": "Lookup",
				"dependsOn": [],
				"policy": {
					"timeout": "0.12:00:00",
					"retry": 0,
					"retryIntervalInSeconds": 30,
					"secureOutput": false,
					"secureInput": false
				},
				"userProperties": [],
				"typeProperties": {
					"source": {
						"type": "AzureSqlSource",
						"sqlReaderQuery": "SELECT * FROM water_table;",
						"queryTimeout": "02:00:00",
						"partitionOption": "None"
					},
					"dataset": {
						"referenceName": "ds_sqldb",
						"type": "DatasetReference",
						"parameters": {
							"table_name": "water_table"
						}
					}
				}
			},
			{
				"name": "current_load",
				"type": "Lookup",
				"dependsOn": [],
				"policy": {
					"timeout": "0.12:00:00",
					"retry": 0,
					"retryIntervalInSeconds": 30,
					"secureOutput": false,
					"secureInput": false
				},
				"userProperties": [],
				"typeProperties": {
					"source": {
						"type": "AzureSqlSource",
						"sqlReaderQuery": "SELECT MAX(Date_ID) as max_date FROM source_cars_data;",
						"queryTimeout": "02:00:00",
						"partitionOption": "None"
					},
					"dataset": {
						"referenceName": "ds_sqldb",
						"type": "DatasetReference",
						"parameters": {
							"table_name": "source_cars_data"
						}
					}
				}
			},
			{
				"name": "WatermarkUpdate",
				"type": "SqlServerStoredProcedure",
				"dependsOn": [
					{
						"activity": "Copy_Increm_Data",
						"dependencyConditions": [
							"Succeeded"
						]
					}
				],
				"policy": {
					"timeout": "0.12:00:00",
					"retry": 0,
					"retryIntervalInSeconds": 30,
					"secureOutput": false,
					"secureInput": false
				},
				"userProperties": [],
				"typeProperties": {
					"storedProcedureName": "[dbo].[UpdateWatermarkTable]",
					"storedProcedureParameters": {
						"lastload": {
							"value": {
								"value": "@activity('current_load').output.firstRow.max_date",
								"type": "Expression"
							},
							"type": "String"
						}
					}
				},
				"linkedServiceName": {
					"referenceName": "ls_sqldb",
					"type": "LinkedServiceReference"
				}
			}
		],
		"annotations": [],
		"lastPublishTime": "2025-07-12T06:37:26Z"
	},
	"type": "Microsoft.DataFactory/factories/pipelines"
}